{
    "시우의 변신!!! 2주 만의 10초 짜리 영상이라니 일해라 시우!!": {
        "title": "시우의 변신!!! 2주 만의 10초 짜리 영상이라니 일해라 시우!!",
        "url": "https://www.youtube.com/watch?v=tW4bs15UYG8",
        "thumbnail_url": "https://i.ytimg.com/vi/tW4bs15UYG8/hq720.jpg"
    },
    "10초 짜리영상 크쿠루삥뽕~~": {
        "title": "10초 짜리영상 크쿠루삥뽕~~",
        "url": "https://www.youtube.com/watch?v=uAmv-8NUGGc",
        "thumbnail_url": "https://i.ytimg.com/vi/uAmv-8NUGGc/hq720.jpg?sqp=-oaymwEmCIAKENAF8quKqQMa8AEB-AH-DoACuAiKAgwIABABGE8gXihlMA8=&rs=AOn4CLC1GYylWFOT6fzlqOtropeRQtgC_g"
    },
    "10초_짜리영상_크쿠루삥뽕": {
        "title": "10초 짜리영상 크쿠루삥뽕~~",
        "url": "https://www.youtube.com/watch?v=uAmv-8NUGGc",
        "thumbnail_url": "https://i.ytimg.com/vi/uAmv-8NUGGc/hq720.jpg?sqp=-oaymwEmCIAKENAF8quKqQMa8AEB-AH-DoACuAiKAgwIABABGE8gXihlMA8=&rs=AOn4CLC1GYylWFOT6fzlqOtropeRQtgC_g"
    },
    "디자인보고_눈뒤집혀서_펀딩한_1위_감성_때려박은_레트로_미니PC_사버림ㅋㅋ": {
        "title": "디자인보고 눈뒤집혀서 펀딩한 1위? 감성 때려박은 레트로 미니PC 사버림ㅋㅋ",
        "url": "https://youtu.be/nspco5QyZwo?si=yPG2ZxNat-ypSQgi",
        "thumbnail_url": "https://i.ytimg.com/vi/nspco5QyZwo/hq720.jpg"
    },
    "심각한_상황": {
        "title": "심각한 상황",
        "url": "https://www.youtube.com/watch?v=NOAJgHm3byg",
        "thumbnail_url": "https://i.ytimg.com/vi/NOAJgHm3byg/hq720.jpg"
    },
    "GitHub으로_협업하기_1편_-_깃헙_프로젝트_생성_이슈_생성_충돌_해결까지": {
        "title": "GitHub으로 협업하기 1편 - 깃헙 프로젝트 생성, 이슈 생성, 충돌 해결까지",
        "url": "https://www.youtube.com/watch?v=6sBNPvxjyt0",
        "thumbnail_url": "https://i.ytimg.com/vi/6sBNPvxjyt0/hq720.jpg"
    },
    "영화관에서_이러면_안돼______EP08_동네꼬마": {
        "title": "영화관에서 이러면 안돼     [ EP.08 동네꼬마 ]",
        "url": "https://www.youtube.com/watch?v=LGs_FnupjOA",
        "thumbnail_url": "https://i.ytimg.com/vi/LGs_FnupjOA/hq720.jpg"
    }
}